sopel_catfact/__init__.py
sopel_catfact/plugin.py
sopel_catfact-0.1.0.dist-info/COPYING
sopel_catfact-0.1.0.dist-info/METADATA
sopel_catfact-0.1.0.dist-info/WHEEL
sopel_catfact-0.1.0.dist-info/entry_points.txt
sopel_catfact-0.1.0.dist-info/top_level.txt
sopel_catfact-0.1.0.dist-info/RECORD
